dsctg/__init__.py
dsctg/script.py
dsctg/webhook.py
dsctg-1.0.1.dist-info/LICENSE
dsctg-1.0.1.dist-info/METADATA
dsctg-1.0.1.dist-info/WHEEL
dsctg-1.0.1.dist-info/top_level.txt
dsctg-1.0.1.dist-info/RECORD
